MANIFEST.in
README.md
requirements.txt
setup.cfg
setup.py
versioneer.py
botcity/plugins/aws/textract/__init__.py
botcity/plugins/aws/textract/_version.py
botcity/plugins/aws/textract/pdfhandler.py
botcity/plugins/aws/textract/plugin.py
botcity_aws_textract_plugin.egg-info/PKG-INFO
botcity_aws_textract_plugin.egg-info/SOURCES.txt
botcity_aws_textract_plugin.egg-info/dependency_links.txt
botcity_aws_textract_plugin.egg-info/requires.txt
botcity_aws_textract_plugin.egg-info/top_level.txt
tests/test_import.py