Metadata-Version: 2.1
Name: botcity-aws-textract-plugin
Version: 0.3.0
Home-page: https://github.com/botcity-dev/bot-aws-textract-plugin-python.git
Requires-Python: >=3.7
